{
  "diagnostic.errorSign": " ",
  "diagnostic.warningSign": " ",
  "diagnostic.infoSign": " ",
  "diagnostic.hintSign": " ",
  "coc.preferences.promptInput": false,
  "coc.preferences.useQuickfixForLocations": true,
  "suggest.noselect": true,
  "suggest.floatConfig": {
    "border": true,
    "rounded": true,
    "borderhighlight": "FloatBorder"
  },
  "diagnostic.floatConfig": {
    "border": true,
    "rounded": true,
    "borderhighlight": "FloatBorder"
  },
  "signature.floatConfig": {
    "border": true,
    "rounded": true,
    "borderhighlight": "FloatBorder"
  },
  "hover.floatConfig": {
    "border": true,
    "rounded": true,
    "borderhighlight": "FloatBorder"
  },
  "dialog.rounded": true,
  "dialog.floatBorderHighlight": "FloatBorder",
  "Lua.diagnostics.globals": ["vim"],
  "@nomicfoundation/coc-solidity.telemetry": false,
  "snippets.textmateSnippetsRoots": ["~/.config/nvim/snippets"],
  "snippets.extends": {
    "javascriptreact": ["javascript"],
    "typescript": ["javascript"],
    "typescriptreact": ["javascript"]
  },
  "languageserver": {
    "tact": {
      "command": "tact-extracted-ls",
      "args": ["--stdio"],
      "filetypes": ["tact"],
      "ignoredRootPaths": ["~"]
    }
  }
}
